{"_invocation_id": "eabe0618-de5d-4db6-8aad-667aa9fbae31", "linked": {"0": {"name": "source.nyc_mobility_project.nyc.fact_taxi_trips", "type": "source", "succ": [4, 7]}, "1": {"name": "source.nyc_mobility_project.nyc.dim_weather", "type": "source", "succ": [5]}, "2": {"name": "model.nyc_mobility_project.high_value_customers", "type": "model"}, "3": {"name": "model.nyc_mobility_project.trip_enriched", "type": "model", "succ": [2, 6]}, "4": {"name": "model.nyc_mobility_project.source_fact_taxi_trips", "type": "model", "succ": [3]}, "5": {"name": "model.nyc_mobility_project.source_dim_weather", "type": "model", "succ": [3]}, "6": {"name": "model.nyc_mobility_project.trip_summary_per_hour", "type": "model"}, "7": {"name": "model.nyc_mobility_project.fact_taxi_trips", "type": "model"}}}